google_trans_new_chiou/__init__.py
google_trans_new_chiou/constant.py
google_trans_new_chiou/google_trans_new.py
google_trans_new_chiou-0.1.0.dist-info/LICENSE
google_trans_new_chiou-0.1.0.dist-info/METADATA
google_trans_new_chiou-0.1.0.dist-info/WHEEL
google_trans_new_chiou-0.1.0.dist-info/top_level.txt
google_trans_new_chiou-0.1.0.dist-info/RECORD
