Metadata-Version: 2.1
Name: google-trans-new-chiou
Version: 0.1.0
Summary: text translation
Home-page: https://github.com/chiou3qorz/google_trans_new_chiou
Author: chiou
Author-email: chiou@e-happy.com.tw
License: UNKNOWN
Keywords: google_translator
Platform: UNKNOWN
Classifier: Programming Language :: Python :: 3
Classifier: License :: OSI Approved :: MIT License
License-File: LICENSE
